CHANGES.rst
MANIFEST.in
Makefile
README.rst
buildout.cfg
heroku.cfg
requirements.txt
setup.py
plonetheme/__init__.py
plonetheme.sunstrap.egg-info/PKG-INFO
plonetheme.sunstrap.egg-info/SOURCES.txt
plonetheme.sunstrap.egg-info/dependency_links.txt
plonetheme.sunstrap.egg-info/entry_points.txt
plonetheme.sunstrap.egg-info/namespace_packages.txt
plonetheme.sunstrap.egg-info/not-zip-safe
plonetheme.sunstrap.egg-info/requires.txt
plonetheme.sunstrap.egg-info/top_level.txt
plonetheme/sunstrap/__init__.py
plonetheme/sunstrap/configure.zcml
plonetheme/sunstrap/profiles/default/metadata.xml
plonetheme/sunstrap/profiles/default/theme.xml
plonetheme/sunstrap/theme/index.html
plonetheme/sunstrap/theme/manifest.cfg
plonetheme/sunstrap/theme/preview.jpg
plonetheme/sunstrap/theme/rules.xml
plonetheme/sunstrap/theme/css/IEFixes.css
plonetheme/sunstrap/theme/css/RTL.css
plonetheme/sunstrap/theme/css/authoring.css
plonetheme/sunstrap/theme/css/base.css
plonetheme/sunstrap/theme/css/carousel.css
plonetheme/sunstrap/theme/css/columns.css
plonetheme/sunstrap/theme/css/contenttypes-sprite.png
plonetheme/sunstrap/theme/css/controlpanel.css
plonetheme/sunstrap/theme/css/deprecated.css
plonetheme/sunstrap/theme/css/dropdown-menu.css
plonetheme/sunstrap/theme/css/forms.css
plonetheme/sunstrap/theme/css/invisibles.css
plonetheme/sunstrap/theme/css/kupuplone.css
plonetheme/sunstrap/theme/css/member.css
plonetheme/sunstrap/theme/css/mobile.css
plonetheme/sunstrap/theme/css/navtree.css
plonetheme/sunstrap/theme/css/ploneCustom.css
plonetheme/sunstrap/theme/css/portlets.css
plonetheme/sunstrap/theme/css/print.css
plonetheme/sunstrap/theme/css/public.css
plonetheme/sunstrap/theme/css/reset.css
plonetheme/sunstrap/theme/js/accessibility.js
plonetheme/sunstrap/theme/js/calendar_formfield.js
plonetheme/sunstrap/theme/js/carousel.js
plonetheme/sunstrap/theme/js/collapsibleformfields.js
plonetheme/sunstrap/theme/js/collapsiblesections.js
plonetheme/sunstrap/theme/js/cookie_functions.js
plonetheme/sunstrap/theme/js/dragdropreorder.js
plonetheme/sunstrap/theme/js/dropdown.js
plonetheme/sunstrap/theme/js/first_input_focus.js
plonetheme/sunstrap/theme/js/formUnload.js
plonetheme/sunstrap/theme/js/form_tabbing.js
plonetheme/sunstrap/theme/js/formsubmithelpers.js
plonetheme/sunstrap/theme/js/fullscreenmode.js
