Metadata-Version: 1.1
Name: plonetheme.sunstrap
Version: 0.0.7
Summary: Plone theme
Home-page: https://github.com/aclark4life/plonetheme.sunstrap
Author: Alex Clark
Author-email: aclark@aclark.net
License: GPL2
Keywords: Bootstrap Diazo Modern Plone Sunburst Theme Theming
Platform: UNKNOWN
Classifier: Framework :: Plone :: 4.3
Classifier: Programming Language :: Python :: 2.7
